iptools/__init__.py
iptools/ipv4.py
iptools/ipv6.py
iptools-0.6.1.dist-info/DESCRIPTION.rst
iptools-0.6.1.dist-info/METADATA
iptools-0.6.1.dist-info/RECORD
iptools-0.6.1.dist-info/WHEEL
iptools-0.6.1.dist-info/metadata.json
iptools-0.6.1.dist-info/top_level.txt
